contextflow/__init__.py
contextflow/core/__init__.py
contextflow/core/compactor.py
contextflow/core/scorer.py
contextflow/core/strategies.py
contextflow/utils/__init__.py
contextflow/utils/llm.py
contextflow/utils/tokenizer.py
contextflow_ai-0.1.3.dist-info/licenses/LICENSE
contextflow_ai-0.1.3.dist-info/METADATA
contextflow_ai-0.1.3.dist-info/WHEEL
contextflow_ai-0.1.3.dist-info/top_level.txt
contextflow_ai-0.1.3.dist-info/RECORD
