Metadata-Version: 2.4
Name: contextflow-ai
Version: 0.1.3
Summary:  Context optimization for AI agents
Author-email: Ayush Thapa <ayushthapa026@gmail.com>
Requires-Python: >=3.10
License-File: LICENSE
Requires-Dist: google-genai==1.49.0
Requires-Dist: click==8.1.7
Requires-Dist: rich==13.9.4
Requires-Dist: python-dotenv==1.0.1
Requires-Dist: numpy==2.3.4
Dynamic: license-file
